uname/__init__.py
uname/uname.py
Uname_sridhar-0.1.3.dist-info/METADATA
Uname_sridhar-0.1.3.dist-info/WHEEL
Uname_sridhar-0.1.3.dist-info/entry_points.txt
Uname_sridhar-0.1.3.dist-info/top_level.txt
Uname_sridhar-0.1.3.dist-info/RECORD
