Metadata-Version: 2.1
Name: Uname_sridhar
Version: 0.1.3
Summary: Uname_sridhar is a wrapper of uname Command
Home-page: https://git.selfmade.ninja/SRIDHARDSCV/package_uname
Author: Sridhar
Author-email: dcsvsridhar@gmail.com
License: UNKNOWN
Platform: UNKNOWN
